{
  "wafv2.rulegroup.customresponsebody.ContentType": {
    "Allowed values": "APPLICATION_JSON | TEXT_HTML | TEXT_PLAIN",
    "Required": "Yes",
    "Type": "String",
    "UpdateRequires": "[No interruption](https://docs.aws.amazon.com/AWSCloudFormation/latest/UserGuide/using-cfn-updating-stacks-update-behaviors.html#update-no-interrupt)"
  },
  "wafv2.rulegroup.customresponsebody.Content": {
    "Pattern": "[\\s\\S]*",
    "Required": "Yes",
    "Maximum": "10240",
    "UpdateRequires": "[No interruption](https://docs.aws.amazon.com/AWSCloudFormation/latest/UserGuide/using-cfn-updating-stacks-update-behaviors.html#update-no-interrupt)",
    "Minimum": "1",
    "Type": "String"
  }
}
