{
  "kendra.datasource.templateconfiguration.CfnAbout": "<a name=\"aws-properties-kendra-datasource-templateconfiguration-description\">",
  "kendra.datasource.templateconfiguration.CfnType": "AWS::Kendra::DataSource.TemplateConfiguration",
  "kendra.datasource.templateconfiguration.CfnDocsKey": "aws-properties-kendra-datasource-templateconfiguration",
  "kendra.datasource.templateconfiguration.Template": {
    "Description": "Property description not available.",
    "Required": "Yes",
    "Type": "String",
    "UpdateRequires": "[No interruption](https://docs.aws.amazon.com/AWSCloudFormation/latest/UserGuide/using-cfn-updating-stacks-update-behaviors.html#update-no-interrupt)"
  }
}
