{
  "iotsitewise.accesspolicy.iamrole.CfnAbout": "Contains information about an AWS Identity and Access Management role. For more information, see [IAM roles](https://docs.aws.amazon.com/IAM/latest/UserGuide/id_roles.html) in the *IAM User Guide*.",
  "iotsitewise.accesspolicy.iamrole.CfnType": "AWS::IoTSiteWise::AccessPolicy.IamRole",
  "iotsitewise.accesspolicy.iamrole.CfnDocsKey": "aws-properties-iotsitewise-accesspolicy-iamrole",
  "iotsitewise.accesspolicy.iamrole.arn": {
    "Description": "The ARN of the IAM role. For more information, see [IAM ARNs](https://docs.aws.amazon.com/IAM/latest/UserGuide/reference_identifiers.html) in the *IAM User Guide*.",
    "Required": "No",
    "Type": "String",
    "UpdateRequires": "No interruption"
  }
}
