{
  "pipes.pipe.deadletterconfig.CfnAbout": "A `DeadLetterConfig` object that contains information about a dead-letter queue configuration.",
  "pipes.pipe.deadletterconfig.CfnType": "AWS::Pipes::Pipe.DeadLetterConfig",
  "pipes.pipe.deadletterconfig.CfnDocsKey": "aws-properties-pipes-pipe-deadletterconfig",
  "pipes.pipe.deadletterconfig.Arn": {
    "Description": "The ARN of the specified target for the dead-letter queue.   For Amazon Kinesis stream and Amazon DynamoDB stream sources, specify either an Amazon SNS topic or Amazon SQS queue ARN.",
    "Required": "No",
    "Type": "String",
    "UpdateRequires": "[No interruption](https://docs.aws.amazon.com/AWSCloudFormation/latest/UserGuide/using-cfn-updating-stacks-update-behaviors.html#update-no-interrupt)"
  }
}
