{
  "iot.domainconfiguration.authorizerconfig.AllowAuthorizerOverride": {
    "Docs": "A Boolean that specifies whether the domain configuration's authorization service can be overridden.",
    "Required": "No",
    "AllowedValues": [
      "True",
      "False"
    ],
    "Type": "Boolean",
    "UpdateRequires": "[No interruption](https://docs.aws.amazon.com/AWSCloudFormation/latest/UserGuide/using-cfn-updating-stacks-update-behaviors.html#update-no-interrupt)"
  },
  "iot.domainconfiguration.authorizerconfig.DefaultAuthorizerName": {
    "Docs": "The name of the authorization service for a domain configuration.",
    "Required": "No",
    "Type": "String",
    "UpdateRequires": "[No interruption](https://docs.aws.amazon.com/AWSCloudFormation/latest/UserGuide/using-cfn-updating-stacks-update-behaviors.html#update-no-interrupt)"
  }
}
