{
  "quicksight.template.radarchartseriessettings.CfnAbout": "The series settings of a radar chart.",
  "quicksight.template.radarchartseriessettings.CfnType": "AWS::QuickSight::Template.RadarChartSeriesSettings",
  "quicksight.template.radarchartseriessettings.CfnDocsKey": "aws-properties-quicksight-template-radarchartseriessettings",
  "quicksight.template.radarchartseriessettings.AreaStyleSettings": {
    "Description": "The area style settings of a radar chart.",
    "Required": "No",
    "Type": "RadarChartAreaStyleSettings",
    "UpdateRequires": "[No interruption](https://docs.aws.amazon.com/AWSCloudFormation/latest/UserGuide/using-cfn-updating-stacks-update-behaviors.html#update-no-interrupt)"
  }
}
