{
  "aws-properties-s3-bucket-inventoryconfiguration-properties": {
    "ScheduleFrequency": {
      "Required": "Yes",
      "Type": "String",
      "UpdateRequires": "No interruption"
    },
    "Destination": {
      "Required": "Yes",
      "Type": "Destination",
      "UpdateRequires": "No interruption"
    },
    "Enabled": {
      "Required": "Yes",
      "Type": "Boolean",
      "UpdateRequires": "No interruption",
      "AllowedValues": [
        "True",
        "False"
      ]
    },
    "OptionalFields": {
      "Required": "No",
      "Type": "List of String",
      "UpdateRequires": "No interruption"
    },
    "Prefix": {
      "Required": "No",
      "Type": "String",
      "UpdateRequires": "No interruption"
    },
    "IncludedObjectVersions": {
      "Required": "Yes",
      "Type": "String",
      "UpdateRequires": "No interruption",
      "AllowedValues": [
        "All",
        "Current"
      ]
    },
    "Id": {
      "Required": "Yes",
      "Type": "String",
      "UpdateRequires": "No interruption"
    }
  }
}
