{
  "quicksight.template.histogramfieldwells.CfnAbout": "The field well configuration of a histogram.",
  "quicksight.template.histogramfieldwells.CfnType": "AWS::QuickSight::Template.HistogramFieldWells",
  "quicksight.template.histogramfieldwells.CfnDocsKey": "aws-properties-quicksight-template-histogramfieldwells",
  "quicksight.template.histogramfieldwells.HistogramAggregatedFieldWells": {
    "Description": "The field well configuration of a histogram.",
    "Required": "No",
    "Type": "HistogramAggregatedFieldWells",
    "UpdateRequires": "[No interruption](https://docs.aws.amazon.com/AWSCloudFormation/latest/UserGuide/using-cfn-updating-stacks-update-behaviors.html#update-no-interrupt)"
  }
}
