{
  "appsync.resolver.pipelineconfig.CfnAbout": "Use the `PipelineConfig` property type to specify `PipelineConfig` for an AWS AppSync resolver.\n\n `PipelineConfig` is a property of the [AWS::AppSync::Resolver](https://docs.aws.amazon.com/AWSCloudFormation/latest/UserGuide/aws-resource-appsync-resolver.html) resource.",
  "appsync.resolver.pipelineconfig.CfnType": "AWS::AppSync::Resolver.PipelineConfig",
  "appsync.resolver.pipelineconfig.CfnDocsKey": "aws-properties-appsync-resolver-pipelineconfig",
  "appsync.resolver.pipelineconfig.Functions": {
    "Description": "A list of `Function` objects.",
    "Required": "No",
    "Type": "List of String",
    "UpdateRequires": "[No interruption](https://docs.aws.amazon.com/AWSCloudFormation/latest/UserGuide/using-cfn-updating-stacks-update-behaviors.html#update-no-interrupt)"
  }
}
