{
  "quicksight.dashboard.freeformlayoutcanvassizeoptions.CfnAbout": "Configuration options for the canvas of a free-form layout.",
  "quicksight.dashboard.freeformlayoutcanvassizeoptions.CfnType": "AWS::QuickSight::Dashboard.FreeFormLayoutCanvasSizeOptions",
  "quicksight.dashboard.freeformlayoutcanvassizeoptions.CfnDocsKey": "aws-properties-quicksight-dashboard-freeformlayoutcanvassizeoptions",
  "quicksight.dashboard.freeformlayoutcanvassizeoptions.ScreenCanvasSizeOptions": {
    "Description": "The options that determine the sizing of the canvas used in a free-form layout.",
    "Required": "No",
    "Type": "FreeFormLayoutScreenCanvasSizeOptions",
    "UpdateRequires": "[No interruption](https://docs.aws.amazon.com/AWSCloudFormation/latest/UserGuide/using-cfn-updating-stacks-update-behaviors.html#update-no-interrupt)"
  }
}
