{
  "apigatewayv2-stage-properties": {
    "ClientCertificateId": {
      "Required": "No",
      "Type": "String",
      "UpdateRequires": "No interruption"
    },
    "Description": {
      "Required": "No",
      "Type": "String",
      "UpdateRequires": "No interruption"
    },
    "AccessLogSettings": {
      "Required": "No",
      "Type": "AccessLogSettings",
      "UpdateRequires": "No interruption"
    },
    "ApiId": {
      "Required": "Yes",
      "Type": "String",
      "UpdateRequires": "Replacement"
    },
    "StageName": {
      "Required": "Yes",
      "Type": "String",
      "UpdateRequires": "Replacement"
    },
    "DeploymentId": {
      "Required": "Yes",
      "Type": "String",
      "UpdateRequires": "No interruption"
    },
    "DefaultRouteSettings": {
      "Required": "No",
      "Type": "RouteSettings",
      "UpdateRequires": "No interruption"
    },
    "StageVariables": {
      "Required": "No",
      "Type": "Json",
      "UpdateRequires": "No interruption"
    },
    "RouteSettings": {
      "Required": "No",
      "Type": "Json",
      "UpdateRequires": "No interruption"
    }
  }
}
