{
  "appmesh.gatewayroute.grpcgatewayroute.Action": {
    "Description": "An object that represents the action to take if a match is determined.",
    "Required": "Yes",
    "Type": "GrpcGatewayRouteAction",
    "UpdateRequires": "[No interruption](https://docs.aws.amazon.com/AWSCloudFormation/latest/UserGuide/using-cfn-updating-stacks-update-behaviors.html#update-no-interrupt)"
  },
  "appmesh.gatewayroute.grpcgatewayroute.Match": {
    "Description": "An object that represents the criteria for determining a request match.",
    "Required": "Yes",
    "Type": "GrpcGatewayRouteMatch",
    "UpdateRequires": "[No interruption](https://docs.aws.amazon.com/AWSCloudFormation/latest/UserGuide/using-cfn-updating-stacks-update-behaviors.html#update-no-interrupt)"
  }
}
