{
  "lightsail.certificate.CertificateName": {
    "Required": "Yes",
    "Type": "String",
    "UpdateRequires": "[Replacement](https://docs.aws.amazon.com/AWSCloudFormation/latest/UserGuide/using-cfn-updating-stacks-update-behaviors.html#update-replacement)"
  },
  "lightsail.certificate.DomainName": {
    "Required": "Yes",
    "Type": "String",
    "UpdateRequires": "Updates are not supported\\."
  },
  "lightsail.certificate.SubjectAlternativeNames": {
    "Required": "No",
    "Type": "List of String",
    "UpdateRequires": "Updates are not supported\\."
  },
  "lightsail.certificate.Tags": {
    "Required": "No",
    "UpdateRequires": "No interruption"
  }
}
