{
  "lex.bot.advancedrecognitionsetting.CfnAbout": "Specifies settings that enable advanced audio recognition for slot values.",
  "lex.bot.advancedrecognitionsetting.CfnType": "AWS::Lex::Bot.AdvancedRecognitionSetting",
  "lex.bot.advancedrecognitionsetting.CfnDocsKey": "aws-properties-lex-bot-advancedrecognitionsetting",
  "lex.bot.advancedrecognitionsetting.AudioRecognitionStrategy": {
    "Description": "Specifies that Amazon Lex should use slot values as a custom vocabulary when recognizing user utterances.",
    "Required": "No",
    "Type": "String",
    "UpdateRequires": "[No interruption](https://docs.aws.amazon.com/AWSCloudFormation/latest/UserGuide/using-cfn-updating-stacks-update-behaviors.html#update-no-interrupt)"
  }
}
