{
  "servicecatalog-cloudformationprovisionedproduct-properties": {
    "AcceptLanguage": {
      "Required": "No",
      "Type": "String",
      "Maximum": "100",
      "UpdateRequires": "No interruption"
    },
    "NotificationArns": {
      "Required": "No",
      "Type": "List of String",
      "Maximum": "5",
      "UpdateRequires": "Replacement"
    },
    "PathId": {
      "Required": "No",
      "Type": "String",
      "Minimum": "1",
      "Maximum": "100",
      "Pattern": "^[a-zA-Z0-9_\\-]*",
      "UpdateRequires": "No interruption"
    },
    "ProductId": {
      "Required": "Conditional",
      "Type": "String",
      "Minimum": "1",
      "Maximum": "100",
      "Pattern": "^[a-zA-Z0-9_\\-]*",
      "UpdateRequires": "No interruption"
    },
    "ProductName": {
      "Required": "Conditional",
      "Type": "String",
      "Minimum": "1",
      "Maximum": "128",
      "Pattern": "[a-zA-Z0-9][a-zA-Z0-9._-]*",
      "UpdateRequires": "No interruption"
    },
    "ProvisionedProductName": {
      "Required": "No",
      "Type": "String",
      "Minimum": "1",
      "Maximum": "128",
      "Pattern": "[a-zA-Z0-9][a-zA-Z0-9._-]*",
      "UpdateRequires": "Replacement"
    },
    "ProvisioningArtifactId": {
      "Required": "Conditional",
      "Type": "String",
      "Minimum": "1",
      "Maximum": "100",
      "Pattern": "^[a-zA-Z0-9_\\-]*",
      "UpdateRequires": "No interruption"
    },
    "ProvisioningArtifactName": {
      "Required": "Conditional",
      "Type": "String",
      "UpdateRequires": "No interruption"
    },
    "ProvisioningParameters": {
      "Required": "No",
      "Type": "List of [ProvisioningParameter",
      "UpdateRequires": "No interruption"
    },
    "ProvisioningPreferences": {
      "Required": "No",
      "Type": "ProvisioningPreferences",
      "UpdateRequires": "No interruption"
    },
    "Tags": {
      "Required": "No",
      "Type": "List of [Tag",
      "Maximum": "50",
      "UpdateRequires": "No interruption"
    }
  }
}
