{
  "ecs.service.placementconstraint.expression": {
    "Required": "No",
    "UpdateRequires": "Replacement"
  },
  "ecs.service.placementconstraint.type": {
    "Required": "Yes",
    "Type": "String",
    "AllowedValues": [
      "distinctInstance",
      "memberOf"
    ],
    "Allowed Values": "distinctInstance | memberOf",
    "UpdateRequires": "[Replacement](https://docs.aws.amazon.com/AWSCloudFormation/latest/UserGuide/using-cfn-updating-stacks-update-behaviors.html#update-replacement)"
  }
}
