{
  "aws-properties-elasticloadbalancingv2-listener-fixedresponseconfig-properties": {
    "ContentType": {
      "Minimum": "0",
      "Required": "No",
      "Type": "String",
      "Maximum": "32",
      "UpdateRequires": "No interruption"
    },
    "MessageBody": {
      "Minimum": "0",
      "Required": "No",
      "Type": "String",
      "Maximum": "1024",
      "UpdateRequires": "No interruption"
    },
    "StatusCode": {
      "Pattern": "^(2|4|5)\\d\\d$",
      "Required": "Yes",
      "Type": "String",
      "UpdateRequires": "No interruption"
    }
  }
}
