{
  "lambda.eventsourcemapping.filtercriteria.CfnAbout": "An object that contains the filters for an event source.",
  "lambda.eventsourcemapping.filtercriteria.CfnType": "AWS::Lambda::EventSourceMapping.FilterCriteria",
  "lambda.eventsourcemapping.filtercriteria.CfnDocsKey": "aws-properties-lambda-eventsourcemapping-filtercriteria",
  "lambda.eventsourcemapping.filtercriteria.Filters": {
    "Description": "A list of filters.",
    "Required": "No",
    "Type": "List of [Filter",
    "UpdateRequires": "[No interruption](https://docs.aws.amazon.com/AWSCloudFormation/latest/UserGuide/using-cfn-updating-stacks-update-behaviors.html#update-no-interrupt)"
  }
}
