{
  "pinpoint.segment.segmentdimensions.location.Country": {
    "Required": "No",
    "Type": "SetDimension",
    "UpdateRequires": "[No interruption](https://docs.aws.amazon.com/AWSCloudFormation/latest/UserGuide/using-cfn-updating-stacks-update-behaviors.html#update-no-interrupt)"
  },
  "pinpoint.segment.segmentdimensions.location.GPSPoint": {
    "Required": "No",
    "Type": "GPSPoint",
    "UpdateRequires": "[No interruption](https://docs.aws.amazon.com/AWSCloudFormation/latest/UserGuide/using-cfn-updating-stacks-update-behaviors.html#update-no-interrupt)"
  }
}
