{
  "appflow.flow.marketosourceproperties.CfnAbout": "The properties that are applied when Marketo is being used as a source.",
  "appflow.flow.marketosourceproperties.CfnType": "AWS::AppFlow::Flow.MarketoSourceProperties",
  "appflow.flow.marketosourceproperties.CfnDocsKey": "aws-properties-appflow-flow-marketosourceproperties",
  "appflow.flow.marketosourceproperties.Object": {
    "Description": "The object specified in the Marketo flow source.",
    "Required": "Yes",
    "Type": "String",
    "Maximum": "512",
    "Pattern": "\\S+",
    "UpdateRequires": "[No interruption](https://docs.aws.amazon.com/AWSCloudFormation/latest/UserGuide/using-cfn-updating-stacks-update-behaviors.html#update-no-interrupt)\n\n#"
  }
}
