{
  "lookoutmetrics.alert.lambdaconfiguration.CfnAbout": "Contains information about a Lambda configuration.",
  "lookoutmetrics.alert.lambdaconfiguration.CfnType": "AWS::LookoutMetrics::Alert.LambdaConfiguration",
  "lookoutmetrics.alert.lambdaconfiguration.CfnDocsKey": "aws-properties-lookoutmetrics-alert-lambdaconfiguration",
  "lookoutmetrics.alert.lambdaconfiguration.LambdaArn": {
    "Description": "The ARN of the Lambda function.",
    "Required": "Yes",
    "Type": "String",
    "UpdateRequires": "[Replacement](https://docs.aws.amazon.com/AWSCloudFormation/latest/UserGuide/using-cfn-updating-stacks-update-behaviors.html#update-replacement)"
  },
  "lookoutmetrics.alert.lambdaconfiguration.RoleArn": {
    "Description": "The ARN of an IAM role that has permission to invoke the Lambda function.",
    "Required": "Yes",
    "Type": "String",
    "UpdateRequires": "[Replacement](https://docs.aws.amazon.com/AWSCloudFormation/latest/UserGuide/using-cfn-updating-stacks-update-behaviors.html#update-replacement)"
  }
}
