{
  "ec2.network.interface.privateipspec.1.Primary": {
    "Required": "Yes",
    "Type": "Boolean",
    "UpdateRequires": "[No interruption](https://docs.aws.amazon.com/AWSCloudFormation/latest/UserGuide/using-cfn-updating-stacks-update-behaviors.html#update-no-interrupt)",
    "AllowedValues": [
      "True",
      "False"
    ]
  },
  "ec2.network.interface.privateipspec.1.PrivateIpAddress": {
    "Required": "Yes",
    "Type": "String",
    "UpdateRequires": "[No interruption](https://docs.aws.amazon.com/AWSCloudFormation/latest/UserGuide/using-cfn-updating-stacks-update-behaviors.html#update-no-interrupt)"
  }
}
