{
  "kinesisanalytics.applicationreferencedatasource.csvmappingparameters.CfnAbout": "Provides additional mapping information when the record format uses delimiters, such as CSV. For example, the following sample records use CSV format, where the records use the *'n'* as the row delimiter and a comma (\",\") as the column delimiter: \n\n `\"name1\", \"address1\"` \n\n `\"name2\", \"address2\"`",
  "kinesisanalytics.applicationreferencedatasource.csvmappingparameters.CfnType": "AWS::KinesisAnalytics::ApplicationReferenceDataSource.CSVMappingParameters",
  "kinesisanalytics.applicationreferencedatasource.csvmappingparameters.CfnDocsKey": "aws-properties-kinesisanalytics-applicationreferencedatasource-csvmappingparameters",
  "kinesisanalytics.applicationreferencedatasource.csvmappingparameters.RecordColumnDelimiter": {
    "Description": "Column delimiter. For example, in a CSV format, a comma (\",\") is the typical column delimiter.",
    "Required": "Yes",
    "Type": "String",
    "Minimum": "1",
    "UpdateRequires": "[No interruption](https://docs.aws.amazon.com/AWSCloudFormation/latest/UserGuide/using-cfn-updating-stacks-update-behaviors.html#update-no-interrupt)"
  },
  "kinesisanalytics.applicationreferencedatasource.csvmappingparameters.RecordRowDelimiter": {
    "Description": "Row delimiter. For example, in a CSV format, *'n'* is the typical row delimiter.",
    "Required": "Yes",
    "Type": "String",
    "Minimum": "1",
    "UpdateRequires": "No interruption"
  }
}
