{
  "guardduty.detector.tagitem.CfnAbout": "<a name=\"aws-properties-guardduty-detector-tagitem-description\">",
  "guardduty.detector.tagitem.CfnType": "AWS::GuardDuty::Detector.TagItem",
  "guardduty.detector.tagitem.CfnDocsKey": "aws-properties-guardduty-detector-tagitem",
  "guardduty.detector.tagitem.Key": {
    "Description": "Property description not available.",
    "Required": "Yes",
    "Type": "String",
    "UpdateRequires": "[No interruption](https://docs.aws.amazon.com/AWSCloudFormation/latest/UserGuide/using-cfn-updating-stacks-update-behaviors.html#update-no-interrupt)"
  },
  "guardduty.detector.tagitem.Value": {
    "Description": "Property description not available.",
    "Required": "Yes",
    "Type": "String",
    "UpdateRequires": "[No interruption](https://docs.aws.amazon.com/AWSCloudFormation/latest/UserGuide/using-cfn-updating-stacks-update-behaviors.html#update-no-interrupt)"
  }
}
