{
  "connect.tasktemplate.defaultfieldvalue.CfnAbout": "Describes a default field and its corresponding value.",
  "connect.tasktemplate.defaultfieldvalue.CfnType": "AWS::Connect::TaskTemplate.DefaultFieldValue",
  "connect.tasktemplate.defaultfieldvalue.CfnDocsKey": "aws-properties-connect-tasktemplate-defaultfieldvalue",
  "connect.tasktemplate.defaultfieldvalue.DefaultValue": {
    "Description": "Default value for the field.",
    "Required": "Yes",
    "Type": "String",
    "UpdateRequires": "[No interruption](https://docs.aws.amazon.com/AWSCloudFormation/latest/UserGuide/using-cfn-updating-stacks-update-behaviors.html#update-no-interrupt)"
  },
  "connect.tasktemplate.defaultfieldvalue.Id": {
    "Description": "Identifier of a field.",
    "Required": "Yes",
    "Type": "FieldIdentifier",
    "UpdateRequires": "[No interruption](https://docs.aws.amazon.com/AWSCloudFormation/latest/UserGuide/using-cfn-updating-stacks-update-behaviors.html#update-no-interrupt)"
  }
}
