{
  "ssmcontacts.contact.targets.ContactTargetInfo": {
    "Required": "No",
    "Type": "Json",
    "UpdateRequires": "[No interruption](https://docs.aws.amazon.com/AWSCloudFormation/latest/UserGuide/using-cfn-updating-stacks-update-behaviors.html#update-no-interrupt)"
  },
  "ssmcontacts.contact.targets.ChannelTargetInfo": {
    "Required": "No",
    "Type": "Json",
    "UpdateRequires": "[No interruption](https://docs.aws.amazon.com/AWSCloudFormation/latest/UserGuide/using-cfn-updating-stacks-update-behaviors.html#update-no-interrupt)"
  }
}
