{
  "acmpca.certificateauthority.accessdescription.AccessLocation": {
    "Docs": "The location of `AccessDescription` information.",
    "Required": "Yes",
    "Type": "GeneralName",
    "UpdateRequires": "[Replacement](https://docs.aws.amazon.com/AWSCloudFormation/latest/UserGuide/using-cfn-updating-stacks-update-behaviors.html#update-replacement)"
  },
  "acmpca.certificateauthority.accessdescription.AccessMethod": {
    "Docs": "The type and format of `AccessDescription` information.",
    "Required": "Yes",
    "Type": "AccessMethod",
    "UpdateRequires": "[Replacement](https://docs.aws.amazon.com/AWSCloudFormation/latest/UserGuide/using-cfn-updating-stacks-update-behaviors.html#update-replacement)"
  }
}
