{
  "ec2.launchtemplate.networkinterfacecount.CfnAbout": "The minimum and maximum number of network interfaces.",
  "ec2.launchtemplate.networkinterfacecount.CfnType": "AWS::EC2::LaunchTemplate.NetworkInterfaceCount",
  "ec2.launchtemplate.networkinterfacecount.CfnDocsKey": "aws-properties-ec2-launchtemplate-networkinterfacecount",
  "ec2.launchtemplate.networkinterfacecount.Max": {
    "Description": "The maximum number of network interfaces. To specify no maximum limit, omit this parameter.",
    "Required": "No",
    "Type": "Integer",
    "UpdateRequires": "[No interruption](https://docs.aws.amazon.com/AWSCloudFormation/latest/UserGuide/using-cfn-updating-stacks-update-behaviors.html#update-no-interrupt)"
  },
  "ec2.launchtemplate.networkinterfacecount.Min": {
    "Description": "The minimum number of network interfaces. To specify no minimum limit, omit this parameter.",
    "Required": "No",
    "Type": "Integer",
    "UpdateRequires": "[No interruption](https://docs.aws.amazon.com/AWSCloudFormation/latest/UserGuide/using-cfn-updating-stacks-update-behaviors.html#update-no-interrupt)"
  }
}
