{
  "aws-properties-route53-recordset-geolocation-1-properties": {
    "ContinentCode": {
      "Required": "No",
      "Type": "String",
      "Minimum": "2",
      "Maximum": "2",
      "UpdateRequires": "No interruption"
    },
    "CountryCode": {
      "Required": "No",
      "Type": "String",
      "Minimum": "1",
      "Maximum": "2",
      "UpdateRequires": "No interruption"
    },
    "SubdivisionCode": {
      "Required": "No",
      "Type": "String",
      "Minimum": "1",
      "Maximum": "3",
      "UpdateRequires": "No interruption"
    }
  }
}
