{
  "aws-properties-ec2-spotfleet-spotfleetrequestconfigdata-launchspecifications-placement-properties": {
    "Tenancy": {
      "Required": "No",
      "Type": "String",
      "UpdateRequires": "No interruption",
      "AllowedValues": [
        "dedicated",
        "default",
        "host"
      ]
    },
    "GroupName": {
      "Required": "No",
      "Type": "String",
      "UpdateRequires": "No interruption"
    },
    "AvailabilityZone": {
      "Required": "No",
      "Type": "String",
      "UpdateRequires": "No interruption"
    }
  }
}
