{
  "iam.user.loginprofile.Password": {
    "Description": "The user's password.",
    "Required": "Yes",
    "Type": "String",
    "UpdateRequires": "[No interruption](https://docs.aws.amazon.com/AWSCloudFormation/latest/UserGuide/using-cfn-updating-stacks-update-behaviors.html#update-no-interrupt)"
  },
  "iam.user.loginprofile.PasswordResetRequired": {
    "Description": "Specifies whether the user is required to set a new password on next sign-in.",
    "Required": "No",
    "AllowedValues": [
      "True",
      "False"
    ],
    "Type": "Boolean",
    "UpdateRequires": "[No interruption](https://docs.aws.amazon.com/AWSCloudFormation/latest/UserGuide/using-cfn-updating-stacks-update-behaviors.html#update-no-interrupt)\n\n#"
  }
}
