{
  "customerprofiles.objecttype.keymap.Name": {
    "Docs": "Name of the key.",
    "Required": "No",
    "Type": "String",
    "UpdateRequires": "[No interruption](https://docs.aws.amazon.com/AWSCloudFormation/latest/UserGuide/using-cfn-updating-stacks-update-behaviors.html#update-no-interrupt)"
  },
  "customerprofiles.objecttype.keymap.ObjectTypeKeyList": {
    "Docs": "A list of ObjectTypeKey.",
    "Required": "No",
    "Type": "List of [ObjectTypeKey",
    "UpdateRequires": "[No interruption](https://docs.aws.amazon.com/AWSCloudFormation/latest/UserGuide/using-cfn-updating-stacks-update-behaviors.html#update-no-interrupt)"
  }
}
