{
  "databrew.job.outputformatoptions.CfnAbout": "Represents a set of options that define the structure of comma-separated (CSV) job output.",
  "databrew.job.outputformatoptions.CfnType": "AWS::DataBrew::Job.OutputFormatOptions",
  "databrew.job.outputformatoptions.CfnDocsKey": "aws-properties-databrew-job-outputformatoptions",
  "databrew.job.outputformatoptions.Csv": {
    "Description": "Represents a set of options that define the structure of comma-separated value (CSV) job output.",
    "Required": "No",
    "Type": "CsvOutputOptions",
    "UpdateRequires": "[No interruption](https://docs.aws.amazon.com/AWSCloudFormation/latest/UserGuide/using-cfn-updating-stacks-update-behaviors.html#update-no-interrupt)"
  }
}
