{
  "quicksight.analysis.sankeydiagramfieldwells.CfnAbout": "The field well configuration of a sankey diagram.",
  "quicksight.analysis.sankeydiagramfieldwells.CfnType": "AWS::QuickSight::Analysis.SankeyDiagramFieldWells",
  "quicksight.analysis.sankeydiagramfieldwells.CfnDocsKey": "aws-properties-quicksight-analysis-sankeydiagramfieldwells",
  "quicksight.analysis.sankeydiagramfieldwells.SankeyDiagramAggregatedFieldWells": {
    "Description": "The field well configuration of a sankey diagram.",
    "Required": "No",
    "Type": "SankeyDiagramAggregatedFieldWells",
    "UpdateRequires": "[No interruption](https://docs.aws.amazon.com/AWSCloudFormation/latest/UserGuide/using-cfn-updating-stacks-update-behaviors.html#update-no-interrupt)"
  }
}
