{
  "databrew.job.statisticoverride.Statistic": {
    "Pattern": "^[A-Z\\_]+$",
    "Required": "Yes",
    "Maximum": "128",
    "UpdateRequires": "[No interruption](https://docs.aws.amazon.com/AWSCloudFormation/latest/UserGuide/using-cfn-updating-stacks-update-behaviors.html#update-no-interrupt)",
    "Minimum": "1",
    "Type": "String"
  },
  "databrew.job.statisticoverride.Parameters": {
    "Required": "Yes",
    "Type": "ParameterMap",
    "UpdateRequires": "[No interruption](https://docs.aws.amazon.com/AWSCloudFormation/latest/UserGuide/using-cfn-updating-stacks-update-behaviors.html#update-no-interrupt)"
  }
}
