{
  "aws-properties-gamelift-fleet-certificateconfiguration-properties": {
    "CertificateType": {
      "Allowed Values": "DISABLED | GENERATED",
      "Required": "Yes",
      "Type": "String",
      "UpdateRequires": "[Replacement](https://docs.aws.amazon.com/AWSCloudFormation/latest/UserGuide/using-cfn-updating-stacks-update-behaviors.html#update-replacement)\n\n#",
      "AllowedValues": [
        "DISABLED",
        "GENERATED"
      ]
    }
  },
  "gamelift.fleet.certificateconfiguration.certificatetype": {
    "Allowed Values": "DISABLED | GENERATED",
    "Required": "Yes",
    "Type": "String",
    "UpdateRequires": "[Replacement](https://docs.aws.amazon.com/AWSCloudFormation/latest/UserGuide/using-cfn-updating-stacks-update-behaviors.html#update-replacement)\n\n#",
    "AllowedValues": [
      "DISABLED",
      "GENERATED"
    ]
  }
}
