{
  "lex.bot.botaliaslocalesettings.CfnAbout": "Specifies settings that are unique to a locale. For example, you can use a different Lambda function for each locale.",
  "lex.bot.botaliaslocalesettings.CfnType": "AWS::Lex::Bot.BotAliasLocaleSettings",
  "lex.bot.botaliaslocalesettings.CfnDocsKey": "aws-properties-lex-bot-botaliaslocalesettings",
  "lex.bot.botaliaslocalesettings.CodeHookSpecification": {
    "Description": "Specifies the Lambda function to use in this locale.",
    "Required": "No",
    "Type": "CodeHookSpecification",
    "UpdateRequires": "[No interruption](https://docs.aws.amazon.com/AWSCloudFormation/latest/UserGuide/using-cfn-updating-stacks-update-behaviors.html#update-no-interrupt)"
  },
  "lex.bot.botaliaslocalesettings.Enabled": {
    "Description": "Specifies whether the locale is enabled for the bot. If the value is false, the locale isn't available for use.",
    "Required": "Yes",
    "AllowedValues": [
      "True",
      "False"
    ],
    "Type": "Boolean",
    "UpdateRequires": "[No interruption](https://docs.aws.amazon.com/AWSCloudFormation/latest/UserGuide/using-cfn-updating-stacks-update-behaviors.html#update-no-interrupt)"
  }
}
