{
  "mediapackage.packagingconfiguration.dashencryption.CfnAbout": "Holds encryption information so that access to the content can be controlled by a DRM solution.",
  "mediapackage.packagingconfiguration.dashencryption.CfnType": "AWS::MediaPackage::PackagingConfiguration.DashEncryption",
  "mediapackage.packagingconfiguration.dashencryption.CfnDocsKey": "aws-properties-mediapackage-packagingconfiguration-dashencryption",
  "mediapackage.packagingconfiguration.dashencryption.SpekeKeyProvider": {
    "Description": "Parameters for the SPEKE key provider.",
    "Required": "Yes",
    "Type": "SpekeKeyProvider",
    "UpdateRequires": "[No interruption](https://docs.aws.amazon.com/AWSCloudFormation/latest/UserGuide/using-cfn-updating-stacks-update-behaviors.html#update-no-interrupt)"
  }
}
