{
  "cognito-identitypool-properties": {
    "AllowUnauthenticatedIdentities": {
      "Required": "Yes",
      "AllowedValues": [
        "True",
        "False"
      ],
      "Type": "Boolean",
      "UpdateRequires": "No interruption"
    },
    "CognitoEvents": {
      "Required": "No",
      "Type": "Json",
      "UpdateRequires": "No interruption"
    },
    "CognitoIdentityProviders": {
      "Required": "No",
      "Type": "List of [CognitoIdentityProvider",
      "UpdateRequires": "No interruption"
    },
    "CognitoStreams": {
      "Required": "No",
      "Type": "CognitoStreams",
      "UpdateRequires": "No interruption"
    },
    "DeveloperProviderName": {
      "Minimum length": "1",
      "Maximum length": "100",
      "Required": "No",
      "Type": "String",
      "UpdateRequires": "No interruption"
    },
    "IdentityPoolName": {
      "Minimum length": "1",
      "Maximum length": "128",
      "Pattern": "[\\w ]+",
      "Required": "No",
      "Type": "String",
      "UpdateRequires": "No interruption"
    },
    "OpenIdConnectProviderARNs": {
      "Required": "No",
      "Type": "List of String",
      "UpdateRequires": "No interruption"
    },
    "PushSync": {
      "Required": "No",
      "Type": "PushSync",
      "UpdateRequires": "No interruption"
    },
    "SamlProviderARNs": {
      "Required": "No",
      "Type": "List of String",
      "UpdateRequires": "No interruption"
    },
    "SupportedLoginProviders": {
      "Required": "No",
      "Type": "Json",
      "UpdateRequires": "No interruption"
    }
  }
}
