{
  "iotthingsgraph.flowtemplate.definitiondocument.CfnAbout": "A document that defines an entity.",
  "iotthingsgraph.flowtemplate.definitiondocument.CfnType": "AWS::IoTThingsGraph::FlowTemplate.DefinitionDocument",
  "iotthingsgraph.flowtemplate.definitiondocument.CfnDocsKey": "aws-properties-iotthingsgraph-flowtemplate-definitiondocument",
  "iotthingsgraph.flowtemplate.definitiondocument.Language": {
    "Description": "The language used to define the entity. `GRAPHQL` is the only valid value.",
    "Required": "Yes",
    "Type": "String",
    "UpdateRequires": "[No interruption](https://docs.aws.amazon.com/AWSCloudFormation/latest/UserGuide/using-cfn-updating-stacks-update-behaviors.html#update-no-interrupt)"
  },
  "iotthingsgraph.flowtemplate.definitiondocument.Text": {
    "Description": "The GraphQL text that defines the entity.",
    "Required": "Yes",
    "Type": "String",
    "UpdateRequires": "[No interruption](https://docs.aws.amazon.com/AWSCloudFormation/latest/UserGuide/using-cfn-updating-stacks-update-behaviors.html#update-no-interrupt)"
  }
}
